{
  "project_info": {
    "project_number": "624048766099",
    "project_id": "maak-dream-crm",
    "storage_bucket": "maak-dream-crm.firebasestorage.app"
  },
  "client": [
    {
      "client_info": {
        "mobilesdk_app_id": "1:624048766099:android:808b6ea63d2d8b71446166",
        "android_client_info": {
          "package_name": "com.vulcantech.maak_dream_crm"
        }
      },
      "oauth_client": [],
      "api_key": [
        {
          "current_key": "AIzaSyAP6SdEY7QmcTnJTsK3kbk4WFBYS7ry_TM"
        }
      ],
      "services": {
        "appinvite_service": {
          "other_platform_oauth_client": []
        }
      }
    }
  ],
  "configuration_version": "1"
}